wideq/__init__.py
wideq/ac.py
wideq/client.py
wideq/core.py
wideq/dishwasher.py
wideq/dryer.py
wideq/refrigerator.py
wideq/util.py
wideq/washer.py
wideq-1.5.0.dist-info/LICENSE
wideq-1.5.0.dist-info/WHEEL
wideq-1.5.0.dist-info/METADATA
wideq-1.5.0.dist-info/RECORD
