Metadata-Version: 2.1
Name: wideq
Version: 1.5.0
Summary: Reverse-engineered client for the LG SmartThinQ API.
Home-page: https://github.com/sampsyo/wideq
License: UNKNOWN
Author: Adrian Sampson
Author-email: adrian@radbox.org
Requires-Python: >=3.6
Requires-Dist: requests
Requires-Dist: responses ; extra == "test"
Provides-Extra: test
